mlm_bias/__init__.py
mlm_bias/__version__.py
mlm_bias/bias_datasets.py
mlm_bias/bias_results.py
mlm_bias/compute_mlm_bias.py
mlm_bias/compute_mlms_relative_bias.py
mlm_bias/utils/__init__.py
mlm_bias/utils/constants.py
mlm_bias/utils/experiments.py
mlm_bias/utils/measures.py
mlm_bias/utils/preprocess.py
mlm_bias/utils/progress.py
mlm_bias-0.1.6.dist-info/LICENSE
mlm_bias-0.1.6.dist-info/METADATA
mlm_bias-0.1.6.dist-info/WHEEL
mlm_bias-0.1.6.dist-info/top_level.txt
mlm_bias-0.1.6.dist-info/RECORD
