Metadata-Version: 2.1
Name: mlm-bias
Version: 0.1.6
Summary: Bias Evaluation Methods for Masked Language Models implemented in PyTorch
Home-page: https://github.com/zalkikar/mlm-bias
Author: Rahul Zalkikar
Author-email: rayzck9@gmail.com
License: MIT
Project-URL: Bug Tracker, https://github.com/zalkikar/mlm-bias/issues
Classifier: Intended Audience :: Developers
Classifier: Intended Audience :: Science/Research
Classifier: License :: OSI Approved :: MIT License
Classifier: Operating System :: OS Independent
Classifier: Programming Language :: Python :: 3
Classifier: Programming Language :: Python :: 3.8
Classifier: Programming Language :: Python :: 3.9
Classifier: Programming Language :: Python :: 3.10
Requires-Python: >=3.8, <3.11
License-File: LICENSE
Requires-Dist: transformers >=4.35.0
Requires-Dist: numpy <2,>=1.23.5
Requires-Dist: pandas >=2.0.3
Requires-Dist: torch >=2.1.0
Requires-Dist: regex >=2023.3.23
